protollm_publish_test/.DS_Store
protollm_publish_test/__init__.py
protollm_publish_test/agents/__init__.py
protollm_publish_test/agents/llama31_agents/__init__.py
protollm_publish_test/agents/llama31_agents/llama31_agent.py
protollm_publish_test/connectors/README.md
protollm_publish_test/connectors/__init__.py
protollm_publish_test/connectors/connector_creator.py
protollm_publish_test/connectors/rest_server.py
protollm_publish_test/connectors/utils.py
protollm_publish_test/definitions.py
protollm_publish_test/ensembles_ma/collect_results.py
protollm_publish_test/metrics/__init__.py
protollm_publish_test/metrics/deepeval_connector.py
protollm_publish_test/metrics/evaluation_metrics.py
protollm_publish_test/rags/__init__.py
protollm_publish_test/rags/configs/chroma.env
protollm_publish_test/rags/configs/docs_processing_config.yaml
protollm_publish_test/rags/configs/elastic.env
protollm_publish_test/rags/jobs.py
protollm_publish_test/rags/pipeline/__init__.py
protollm_publish_test/rags/pipeline/docs_processing/__init__.py
protollm_publish_test/rags/pipeline/docs_processing/entities.py
protollm_publish_test/rags/pipeline/docs_processing/exceptions.py
protollm_publish_test/rags/pipeline/docs_processing/models.py
protollm_publish_test/rags/pipeline/docs_processing/utils.py
protollm_publish_test/rags/pipeline/etl_pipeline.py
protollm_publish_test/rags/rag_core/__init__.py
protollm_publish_test/rags/rag_core/planner.py
protollm_publish_test/rags/rag_core/reranker.py
protollm_publish_test/rags/rag_core/retriever.py
protollm_publish_test/rags/rag_core/utils.py
protollm_publish_test/rags/settings/__init__.py
protollm_publish_test/rags/settings/chroma_settings.py
protollm_publish_test/rags/settings/es_settings.py
protollm_publish_test/rags/settings/pipeline_settings.py
protollm_publish_test/rags/stores/__init__.py
protollm_publish_test/rags/stores/chroma/__init__.py
protollm_publish_test/rags/stores/chroma/chroma_loader.py
protollm_publish_test/rags/stores/chroma/utils.py
protollm_publish_test-0.1.2.dist-info/LICENSE
protollm_publish_test-0.1.2.dist-info/METADATA
protollm_publish_test-0.1.2.dist-info/WHEEL
protollm_publish_test-0.1.2.dist-info/RECORD
