Metadata-Version: 2.3
Name: ProtoLLM_publish_test
Version: 0.1.2
Summary: 
Author: Kamil Fatkhiev
Requires-Python: >=3.10,<4.0
Classifier: Programming Language :: Python :: 3
Classifier: Programming Language :: Python :: 3.10
Classifier: Programming Language :: Python :: 3.11
Classifier: Programming Language :: Python :: 3.12
Classifier: Programming Language :: Python :: 3.13
Requires-Dist: aioredis (>=2.0.1,<3.0.0)
Requires-Dist: celery (>=5.4.0,<6.0.0)
Requires-Dist: deepeval (==2.3.3) ; python_version >= "3.10" and python_version < "3.14"
Requires-Dist: fastapi (>=0.111.0,<0.112.0)
Requires-Dist: flower (>=2.0.1,<3.0.0)
Requires-Dist: httpx (>=0.27.0,<0.28.0)
Requires-Dist: kombu (>=5.3.7,<6.0.0)
Requires-Dist: langchain (>=0.3.4,<0.4.0)
Requires-Dist: langchain-gigachat (==0.3.3)
Requires-Dist: langchain-openai (==0.3.3)
Requires-Dist: openai (>=1.42.0,<2.0.0)
Requires-Dist: pika (>=1.3.2,<2.0.0)
Requires-Dist: pydantic (>=2.7.4,<3.0.0)
Requires-Dist: pydantic-core (==2.23.4)
Requires-Dist: redis (>=5.0.6,<6.0.0)
Requires-Dist: requests (>=2.32.3,<3.0.0)
Requires-Dist: tornado (>=6.4.1,<7.0.0)
Requires-Dist: urllib3 (>=2.2.2,<3.0.0)
Requires-Dist: uuid (>=1.30,<2.0)
